MANIFEST.in
README.rst
setup.py
http_signature/__init__.py
http_signature/requests_auth.py
http_signature/sign.py
http_signature/utils.py
http_signature.egg-info/PKG-INFO
http_signature.egg-info/SOURCES.txt
http_signature.egg-info/dependency_links.txt
http_signature.egg-info/requires.txt
http_signature.egg-info/top_level.txt
http_signature.egg-info/zip-safe