Metadata-Version: 1.0
Name: http-signature
Version: 0.1.2
Summary: Simple secure signing for HTTP requests using http-signature
Home-page: https://github.com/atl/py-http-signature
Author: Adam T. Lindsay
Author-email: a.lindsay+github@gmail.com
License: MIT
Keywords: http,cryptography,web,joyent
Platform: UNKNOWN
Classifier: Programming Language :: Python
Classifier: Topic :: Software Development :: Libraries :: Python Modules
Classifier: Topic :: Internet :: WWW/HTTP
Classifier: Environment :: Web Environment
Classifier: Topic :: Internet :: WWW/HTTP :: Site Management
Classifier: Intended Audience :: Developers
Classifier: License :: OSI Approved :: MIT License
Classifier: Development Status :: 3 - Alpha
